ornekmodul/__init__.py
ornekmodul/main.py
ornekmodul-1.0.0.dist-info/METADATA
ornekmodul-1.0.0.dist-info/WHEEL
ornekmodul-1.0.0.dist-info/top_level.txt
ornekmodul-1.0.0.dist-info/RECORD
