Metadata-Version: 2.4
Name: ornekmodul
Version: 1.0.0
Summary: Basit bir hesaplayıcı modülü
